Metadata-Version: 2.1
Name: u2x
Version: 0.0.2
Summary: A python util package
Home-page: https://github.com/xuebinqin/U-2-Net
Author: cvdnn
Author-email: cvvdnn@gmail.com
License: UNKNOWN
Project-URL: Bug Tracker, https://github.com/xuebinqin/U-2-Net/issues
Keywords: pip,license,image,tool
Platform: UNKNOWN
Classifier: Programming Language :: Python :: 3
Classifier: License :: OSI Approved :: MIT License
Classifier: Operating System :: OS Independent
Requires-Python: >=3.6
License-File: LICENSE
